event_people/__init__.py
event_people/config.py
event_people/daemon.py
event_people/emitter.py
event_people/event.py
event_people/listener.py
event_people/broker/__init__.py
event_people/broker/base.py
event_people/broker/rabbit_broker.py
event_people/broker/rabbit/__init__.py
event_people/broker/rabbit/context.py
event_people/broker/rabbit/queue.py
event_people/broker/rabbit/topic.py
event_people/listeners/__init__.py
event_people/listeners/base_listener.py
event_people/listeners/listener_manager.py
event_people-0.0.3.dist-info/METADATA
event_people-0.0.3.dist-info/WHEEL
event_people-0.0.3.dist-info/licenses/LICENSE
event_people-0.0.3.dist-info/RECORD
