Metadata-Version: 2.1
Name: event_people
Version: 0.0.3
Summary: Tool to simplify the communication of event based services.
Project-URL: Homepage, https://github.com/pin-people/event_people_python
Project-URL: Bug Tracker, https://github.com/pin-people/event_people_python/issues
Author-email: Pin People <tech@pinpeople.com.br>
License-File: LICENSE
Classifier: License :: OSI Approved :: GNU Lesser General Public License v3 (LGPLv3)
Classifier: Operating System :: OS Independent
Classifier: Programming Language :: Python :: 3
Requires-Python: >=3.7
Requires-Dist: pika
